wagtailpurge/__init__.py
wagtailpurge/apps.py
wagtailpurge/constants.py
wagtailpurge/filters.py
wagtailpurge/forms.py
wagtailpurge/modeladmin.py
wagtailpurge/models.py
wagtailpurge/test_modeladmin.py
wagtailpurge/test_models.py
wagtailpurge/test_views.py
wagtailpurge/views.py
wagtailpurge/wagtail_hooks.py
wagtailpurge/migrations/0001_initial.py
wagtailpurge/migrations/0002_urlpurgerequest.py
wagtailpurge/migrations/__init__.py
wagtailpurge/templates/modeladmin/wagtailpurge/create.html
wagtailpurge/testapp/models.py
wagtailpurge/testapp/settings.py
wagtailpurge/testapp/urls.py
wagtailpurge/testapp/utils.py
wagtailpurge/testapp/migrations/0001_initial.py
wagtailpurge/testapp/migrations/__init__.py
wagtailpurge-1.0.dist-info/LICENSE
wagtailpurge-1.0.dist-info/METADATA
wagtailpurge-1.0.dist-info/WHEEL
wagtailpurge-1.0.dist-info/top_level.txt
wagtailpurge-1.0.dist-info/RECORD
