Metadata-Version: 2.1
Name: wagtailpurge
Version: 1.0
Author: Andy Babic
Author-email: andyjbabic@gmail.com
License: MIT
Keywords: wagtail cms cache caches purge clear invalidate renditions utility
Classifier: Environment :: Web Environment
Classifier: Development Status :: 4 - Beta
Classifier: Intended Audience :: Developers
Classifier: Operating System :: OS Independent
Classifier: Natural Language :: English
Classifier: License :: OSI Approved :: MIT License
Classifier: Programming Language :: Python
Classifier: Programming Language :: Python :: 3.7
Classifier: Programming Language :: Python :: 3.8
Classifier: Programming Language :: Python :: 3.9
Classifier: Framework :: Django
Classifier: Framework :: Django :: 3.2
Classifier: Framework :: Django :: 4
Classifier: Framework :: Wagtail
Classifier: Framework :: Wagtail :: 2
Classifier: Framework :: Wagtail :: 3
Classifier: Framework :: Wagtail :: 4
Requires-Python: >=3.6
License-File: LICENSE
Requires-Dist: Wagtail (>=2.16)
Requires-Dist: Django (>=3.2)
Provides-Extra: lint
Requires-Dist: black (==22.8.0) ; extra == 'lint'
Requires-Dist: isort (==5.10.1) ; extra == 'lint'
Requires-Dist: flake8 (==5.0.4) ; extra == 'lint'
Provides-Extra: test
Requires-Dist: pytest-cov (==4.0.0) ; extra == 'test'
Requires-Dist: pytest-mock (==3.9.0) ; extra == 'test'
Requires-Dist: pytest-django (==4.5.2) ; extra == 'test'
Requires-Dist: pytest (==7.1.3) ; extra == 'test'
